mlgram/__init__.py
mlgram/mlgram.py
mlgram-0.0b0.dist-info/LICENSE
mlgram-0.0b0.dist-info/METADATA
mlgram-0.0b0.dist-info/WHEEL
mlgram-0.0b0.dist-info/top_level.txt
mlgram-0.0b0.dist-info/RECORD
